{
"type": "FeatureCollection",
"name": "labels_3",
"crs": { "type": "name", "properties": { "name": "urn:ogc:def:crs:OGC:1.3:CRS84" } },
"features": [
{ "type": "Feature", "properties": { "fid": 1, "label": "Pull-through / Tiny Home Sites", "col": "#2fa7fc" }, "geometry": { "type": "Point", "coordinates": [ -120.046257501289759, 51.940250931062003 ] } },
{ "type": "Feature", "properties": { "fid": 2, "label": "Regular RV Sites", "col": "#ffc56d" }, "geometry": { "type": "Point", "coordinates": [ -120.047574916480585, 51.939575284921453 ] } }
]
}
