{
"type": "FeatureCollection",
"name": "labels",
"crs": { "type": "name", "properties": { "name": "urn:ogc:def:crs:OGC:1.3:CRS84" } },
"features": [
{ "type": "Feature", "properties": { "fid": 3, "label": "Full Service Sites", "col": "#45bb69" }, "geometry": { "type": "Point", "coordinates": [ -120.047826439943222, 51.940257349355193 ] } },
{ "type": "Feature", "properties": { "fid": 4, "label": "Power / Water Sites", "col": "#2fa7fc" }, "geometry": { "type": "Point", "coordinates": [ -120.048169107237868, 51.939699923684302 ] } }
]
}
