{"type": "FeatureCollection", "name": "labels", "crs": {"type": "name", "properties": {"name": "urn:ogc:def:crs:OGC:1.3:CRS84"}}, "features": [{"type": "Feature", "properties": {"fid": 3, "label": "Full-Service RV Sites", "col": "#45bb69"}, "geometry": {"type": "Point", "coordinates": [-120.04782643994322, 51.94025734935519]}}, {"type": "Feature", "properties": {"fid": 4, "label": "Power & Water RV Sites", "col": "#2fa7fc"}, "geometry": {"type": "Point", "coordinates": [-120.04816910723787, 51.9396999236843]}}]}