{
"type": "FeatureCollection",
"name": "pedestals_3",
"crs": { "type": "name", "properties": { "name": "urn:ogc:def:crs:OGC:1.3:CRS84" } },
"features": [
{ "type": "Feature", "properties": { "fid": 6, "id": 0 }, "geometry": { "type": "Point", "coordinates": [ -120.047813033139946, 51.936186684809492 ] } },
{ "type": "Feature", "properties": { "fid": 7, "id": 1 }, "geometry": { "type": "Point", "coordinates": [ -120.047753110229564, 51.936258197018908 ] } },
{ "type": "Feature", "properties": { "fid": 8, "id": 2 }, "geometry": { "type": "Point", "coordinates": [ -120.047705479713926, 51.936333511448602 ] } },
{ "type": "Feature", "properties": { "fid": 9, "id": 3 }, "geometry": { "type": "Point", "coordinates": [ -120.047675584025939, 51.936412207699625 ] } },
{ "type": "Feature", "properties": { "fid": 10, "id": 4 }, "geometry": { "type": "Point", "coordinates": [ -120.047647553633468, 51.93649120869128 ] } },
{ "type": "Feature", "properties": { "fid": 11, "id": 5 }, "geometry": { "type": "Point", "coordinates": [ -120.04764054990541, 51.936571757628933 ] } },
{ "type": "Feature", "properties": { "fid": 12, "id": 6 }, "geometry": { "type": "Point", "coordinates": [ -120.047642714612309, 51.936652579265456 ] } },
{ "type": "Feature", "properties": { "fid": 13, "id": 7 }, "geometry": { "type": "Point", "coordinates": [ -120.047662802141915, 51.936732491230472 ] } },
{ "type": "Feature", "properties": { "fid": 14, "id": 8 }, "geometry": { "type": "Point", "coordinates": [ -120.047694287613197, 51.936810848171234 ] } },
{ "type": "Feature", "properties": { "fid": 15, "id": 9 }, "geometry": { "type": "Point", "coordinates": [ -120.047732914846492, 51.93688811959143 ] } },
{ "type": "Feature", "properties": { "fid": 16, "id": 10 }, "geometry": { "type": "Point", "coordinates": [ -120.047785374212523, 51.936962197755314 ] } },
{ "type": "Feature", "properties": { "fid": 17, "id": 11 }, "geometry": { "type": "Point", "coordinates": [ -120.047846760681594, 51.93703329883229 ] } },
{ "type": "Feature", "properties": { "fid": 18, "id": 12 }, "geometry": { "type": "Point", "coordinates": [ -120.047927098592268, 51.937097138431014 ] } },
{ "type": "Feature", "properties": { "fid": 19, "id": 13 }, "geometry": { "type": "Point", "coordinates": [ -120.04802107314319, 51.937152296391552 ] } },
{ "type": "Feature", "properties": { "fid": 20, "id": 14 }, "geometry": { "type": "Point", "coordinates": [ -120.047602454051273, 51.936122498017987 ] } },
{ "type": "Feature", "properties": { "fid": 21, "id": 15 }, "geometry": { "type": "Point", "coordinates": [ -120.047543714459593, 51.936194568619953 ] } },
{ "type": "Feature", "properties": { "fid": 22, "id": 16 }, "geometry": { "type": "Point", "coordinates": [ -120.047495344809235, 51.93626971812612 ] } },
{ "type": "Feature", "properties": { "fid": 23, "id": 17 }, "geometry": { "type": "Point", "coordinates": [ -120.047460380757244, 51.936347547214687 ] } },
{ "type": "Feature", "properties": { "fid": 24, "id": 18 }, "geometry": { "type": "Point", "coordinates": [ -120.047432350033489, 51.936426548150614 ] } },
{ "type": "Feature", "properties": { "fid": 25, "id": 19 }, "geometry": { "type": "Point", "coordinates": [ -120.047409288274238, 51.936506076174894 ] } },
{ "type": "Feature", "properties": { "fid": 26, "id": 20 }, "geometry": { "type": "Point", "coordinates": [ -120.04740793179289, 51.936586937685639 ] } },
{ "type": "Feature", "properties": { "fid": 27, "id": 21 }, "geometry": { "type": "Point", "coordinates": [ -120.047411754852305, 51.936667713044251 ] } },
{ "type": "Feature", "properties": { "fid": 28, "id": 22 }, "geometry": { "type": "Point", "coordinates": [ -120.047431166625657, 51.936747679508422 ] } },
{ "type": "Feature", "properties": { "fid": 29, "id": 23 }, "geometry": { "type": "Point", "coordinates": [ -120.047458819561726, 51.936826629118755 ] } },
{ "type": "Feature", "properties": { "fid": 30, "id": 24 }, "geometry": { "type": "Point", "coordinates": [ -120.047497144712466, 51.936903960684148 ] } },
{ "type": "Feature", "properties": { "fid": 31, "id": 25 }, "geometry": { "type": "Point", "coordinates": [ -120.047543122385093, 51.936979579243747 ] } },
{ "type": "Feature", "properties": { "fid": 32, "id": 26 }, "geometry": { "type": "Point", "coordinates": [ -120.047596548829588, 51.937053408848662 ] } },
{ "type": "Feature", "properties": { "fid": 33, "id": 27 }, "geometry": { "type": "Point", "coordinates": [ -120.04766417783334, 51.937122397599218 ] } },
{ "type": "Feature", "properties": { "fid": 34, "id": 28 }, "geometry": { "type": "Point", "coordinates": [ -120.047744515633823, 51.937186237320283 ] } },
{ "type": "Feature", "properties": { "fid": 35, "id": 29 }, "geometry": { "type": "Point", "coordinates": [ -120.047832415340949, 51.937245880663667 ] } },
{ "type": "Feature", "properties": { "fid": 36, "id": 30 }, "geometry": { "type": "Point", "coordinates": [ -120.047942966217207, 51.937288668740472 ] } }
]
}
