{
"type": "FeatureCollection",
"name": "water_service_4",
"crs": { "type": "name", "properties": { "name": "urn:ogc:def:crs:OGC:1.3:CRS84" } },
"features": [
{ "type": "Feature", "properties": { "fid": 1, "id": 0 }, "geometry": { "type": "Point", "coordinates": [ -120.056592481404124, 51.93686288376032 ] } }
]
}
